pdfcropper/__init__.py
pdfcropper/command_line.py
pdfcropper/config.py
pdfcropper/crop_png.py
pdfcropper/pdf_to_png.py
pdfcropper/utils/__init__.py
pdfcropper/utils/error.py
pdf_image_cropper-0.1.6.dist-info/LICENSE.txt
pdf_image_cropper-0.1.6.dist-info/METADATA
pdf_image_cropper-0.1.6.dist-info/WHEEL
pdf_image_cropper-0.1.6.dist-info/entry_points.txt
pdf_image_cropper-0.1.6.dist-info/top_level.txt
pdf_image_cropper-0.1.6.dist-info/RECORD
