Metadata-Version: 2.1
Name: pdf-image-cropper
Version: 0.1.6
Summary: Crop pdf and conver to png
Home-page: https://gitlab.com/ali7line/awesome-scripts/-/tree/master/pdfcropper
Author: Ali Soltani
Author-email: realalisoltani@gmail.com
License: MIT
Keywords: pdf crop png
Platform: POSIX
Classifier: Development Status :: 1 - Planning
Classifier: Intended Audience :: Science/Research
Classifier: Environment :: Console
Classifier: License :: OSI Approved :: MIT License
Classifier: Operating System :: POSIX
Classifier: Programming Language :: Python :: 3.7
Requires-Python: >=3.7
License-File: LICENSE.txt
Requires-Dist: pyyaml
Requires-Dist: opencv-python
Requires-Dist: numpy
Requires-Dist: pymupdf
Requires-Dist: Pillow
